codepeek/__init__.py
codepeek/cli.py
codepeek/codepeek.py
codepeek/constants.py
codepeek/extractor.py
codepeek/utils.py
codepeek/analyzer/__init__.py
codepeek/analyzer/ai_analyzer.py
codepeek/analyzer/local_analyzer.py
codepeek/analyzer/pdf_reporter.py
codepeek/analyzer/suggestion_model.py
codepeek-2.0.2.dist-info/licenses/LICENSE
codepeek-2.0.2.dist-info/METADATA
codepeek-2.0.2.dist-info/WHEEL
codepeek-2.0.2.dist-info/entry_points.txt
codepeek-2.0.2.dist-info/top_level.txt
codepeek-2.0.2.dist-info/RECORD
