Metadata-Version: 2.4
Name: codepeek
Version: 2.0.2
Summary: Extract and analyze codebases from GitHub or local directories using AI (SOLID, Design Patterns, Security, Architecture)
Author-email: Ahmed Abd Alzeez <ahmedabdalziz.1886@gmail.com>
License-Expression: MIT
Requires-Python: >=3.8
License-File: LICENSE
Requires-Dist: requests
Requires-Dist: tqdm
Requires-Dist: reportlab
Requires-Dist: python-dotenv
Dynamic: license-file
